xeppelin/__init__.py
xeppelin/xeppelin.py
xeppelin/xeppelin.sh
xeppelin/xeppelin_logging.py
xeppelin-0.3.3.dist-info/METADATA
xeppelin-0.3.3.dist-info/WHEEL
xeppelin-0.3.3.dist-info/entry_points.txt
xeppelin-0.3.3.dist-info/top_level.txt
xeppelin-0.3.3.dist-info/RECORD
