Metadata-Version: 2.4
Name: xeppelin
Version: 0.3.3
Summary: Xeppelin Contest Watcher
Home-page: https://github.com/kik0s/xeppelin
Author: Konstantin Amelichev
Author-email: kostya.amelichev@gmail.com
Classifier: Programming Language :: Python :: 3
Classifier: License :: OSI Approved :: MIT License
Classifier: Operating System :: OS Independent
Requires-Python: >=3.6
Requires-Dist: pandas
Requires-Dist: matplotlib
Requires-Dist: numpy
Dynamic: author
Dynamic: author-email
Dynamic: classifier
Dynamic: description
Dynamic: description-content-type
Dynamic: home-page
Dynamic: requires-dist
Dynamic: requires-python
Dynamic: summary
